cpGrader/__init__.py
cpGrader/config.py
cpGrader/cpGrader.py
cpGrader/testcase.py
cpGrader/utils.py
cpgrader-0.1.4.dist-info/LICENSE
cpgrader-0.1.4.dist-info/METADATA
cpgrader-0.1.4.dist-info/WHEEL
cpgrader-0.1.4.dist-info/RECORD
