Metadata-Version: 2.1
Name: cpGrader
Version: 0.1.4
Summary: A Python Package to Grade Programming Assignments Automatically.
Author: ryanlinjui
Author-email: ryanlinjui@gmail.com
Requires-Python: >=3.8,<4.0
Classifier: Programming Language :: Python :: 3
Classifier: Programming Language :: Python :: 3.8
Classifier: Programming Language :: Python :: 3.9
Classifier: Programming Language :: Python :: 3.10
Classifier: Programming Language :: Python :: 3.11
Classifier: Programming Language :: Python :: 3.12
Requires-Dist: objprint (>=0.2.3,<0.3.0)
Requires-Dist: pexpect (>=4.9.0,<5.0.0)
Requires-Dist: toml (>=0.10.2,<0.11.0)
